{
    "swagger": "2.0",
    "info": {
        "contact": {}
    },
    "paths": {
        "/courses": {
            "get": {
                "description": "Get list of courses",
                "consumes": [
                    "application/json"
                ],
                "produces": [
                    "application/json"
                ],
                "tags": [
                    "courses"
                ],
                "summary": "Get list of courses",
                "responses": {
                    "200": {
                        "description": "OK",
                        "schema": {
                            "$ref": "#/definitions/models.GetListCourseResponse"
                        }
                    },
                    "500": {
                        "description": "Internal Server Error",
                        "schema": {
                            "$ref": "#/definitions/models.DefaultError"
                        }
                    }
                }
            },
            "post": {
                "description": "Create a new course with the input payload",
                "consumes": [
                    "application/json"
                ],
                "produces": [
                    "application/json"
                ],
                "tags": [
                    "courses"
                ],
                "summary": "Create a new course",
                "parameters": [
                    {
                        "description": "Create Course",
                        "name": "course",
                        "in": "body",
                        "required": true,
                        "schema": {
                            "$ref": "#/definitions/models.CreateCourse"
                        }
                    }
                ],
                "responses": {
                    "200": {
                        "description": "OK",
                        "schema": {
                            "$ref": "#/definitions/models.SuccessResponse"
                        }
                    },
                    "400": {
                        "description": "Bad Request",
                        "schema": {
                            "$ref": "#/definitions/models.DefaultError"
                        }
                    },
                    "500": {
                        "description": "Internal Server Error",
                        "schema": {
                            "$ref": "#/definitions/models.DefaultError"
                        }
                    }
                }
            }
        },
        "/courses/{id}": {
            "get": {
                "description": "Get a course by ID",
                "consumes": [
                    "application/json"
                ],
                "produces": [
                    "application/json"
                ],
                "tags": [
                    "courses"
                ],
                "summary": "Get a course by ID",
                "parameters": [
                    {
                        "type": "integer",
                        "description": "Course ID",
                        "name": "id",
                        "in": "path",
                        "required": true
                    }
                ],
                "responses": {
                    "200": {
                        "description": "OK",
                        "schema": {
                            "$ref": "#/definitions/models.SuccessResponse"
                        }
                    },
                    "400": {
                        "description": "Bad Request",
                        "schema": {
                            "$ref": "#/definitions/models.DefaultError"
                        }
                    },
                    "404": {
                        "description": "Not Found",
                        "schema": {
                            "$ref": "#/definitions/models.DefaultError"
                        }
                    }
                }
            },
            "put": {
                "description": "Update an existing course with the input payload",
                "consumes": [
                    "application/json"
                ],
                "produces": [
                    "application/json"
                ],
                "tags": [
                    "courses"
                ],
                "summary": "Update an existing course",
                "parameters": [
                    {
                        "type": "integer",
                        "description": "Course ID",
                        "name": "id",
                        "in": "path",
                        "required": true
                    },
                    {
                        "description": "Update Course",
                        "name": "course",
                        "in": "body",
                        "required": true,
                        "schema": {
                            "$ref": "#/definitions/models.UpdateCourse"
                        }
                    }
                ],
                "responses": {
                    "200": {
                        "description": "OK",
                        "schema": {
                            "$ref": "#/definitions/models.SuccessResponse"
                        }
                    },
                    "400": {
                        "description": "Bad Request",
                        "schema": {
                            "$ref": "#/definitions/models.DefaultError"
                        }
                    },
                    "500": {
                        "description": "Internal Server Error",
                        "schema": {
                            "$ref": "#/definitions/models.DefaultError"
                        }
                    }
                }
            },
            "delete": {
                "description": "Delete a course by ID",
                "consumes": [
                    "application/json"
                ],
                "produces": [
                    "application/json"
                ],
                "tags": [
                    "courses"
                ],
                "summary": "Delete a course by ID",
                "parameters": [
                    {
                        "type": "integer",
                        "description": "Course ID",
                        "name": "id",
                        "in": "path",
                        "required": true
                    }
                ],
                "responses": {
                    "200": {
                        "description": "OK",
                        "schema": {
                            "$ref": "#/definitions/models.SuccessResponse"
                        }
                    },
                    "400": {
                        "description": "Bad Request",
                        "schema": {
                            "$ref": "#/definitions/models.DefaultError"
                        }
                    },
                    "500": {
                        "description": "Internal Server Error",
                        "schema": {
                            "$ref": "#/definitions/models.DefaultError"
                        }
                    }
                }
            }
        }
    },
    "definitions": {
        "models.Course": {
            "type": "object",
            "properties": {
                "created_at": {
                    "type": "string"
                },
                "description": {
                    "type": "string"
                },
                "id": {
                    "type": "integer"
                },
                "price_no_tutor": {
                    "type": "number"
                },
                "price_tutor": {
                    "type": "number"
                },
                "title": {
                    "type": "string"
                },
                "updated_at": {
                    "type": "string"
                }
            }
        },
        "models.CreateCourse": {
            "type": "object",
            "properties": {
                "description": {
                    "type": "string"
                },
                "price_no_tutor": {
                    "type": "number"
                },
                "price_tutor": {
                    "type": "number"
                },
                "title": {
                    "type": "string"
                }
            }
        },
        "models.DefaultError": {
            "type": "object",
            "properties": {
                "message": {
                    "type": "string"
                }
            }
        },
        "models.GetListCourseResponse": {
            "type": "object",
            "properties": {
                "count": {
                    "type": "integer"
                },
                "courses": {
                    "type": "array",
                    "items": {
                        "$ref": "#/definitions/models.Course"
                    }
                }
            }
        },
        "models.SuccessResponse": {
            "type": "object",
            "properties": {
                "data": {},
                "message": {
                    "type": "string"
                }
            }
        },
        "models.UpdateCourse": {
            "type": "object",
            "properties": {
                "description": {
                    "type": "string"
                },
                "id": {
                    "type": "integer"
                },
                "price_no_tutor": {
                    "type": "number"
                },
                "price_tutor": {
                    "type": "number"
                },
                "title": {
                    "type": "string"
                }
            }
        }
    }
}